pypentair/__init__.py
pypentair/const.py
pypentair/exceptions.py
pypentair/pentair.py
pypentair/py.typed
pypentair/utils.py
pypentair-0.4.0.dist-info/METADATA
pypentair-0.4.0.dist-info/WHEEL
pypentair-0.4.0.dist-info/licenses/LICENSE
pypentair-0.4.0.dist-info/RECORD
