Metadata-Version: 2.4
Name: pypentair
Version: 0.4.0
Summary: Python package for interacting with Pentair Home devices
License-Expression: MIT
License-File: LICENSE
Keywords: Pentair,Pentair Home,salt level sensor,python
Author: Nathan Spencer
Author-email: natekspencer@gmail.com
Requires-Python: >=3.10
Classifier: Programming Language :: Python :: 3
Classifier: Programming Language :: Python :: 3.10
Classifier: Programming Language :: Python :: 3.11
Classifier: Programming Language :: Python :: 3.12
Classifier: Programming Language :: Python :: 3.13
Classifier: Programming Language :: Python :: 3.14
Requires-Dist: boto3 (>=1.27.1)
Requires-Dist: pycognito (>=2023.5)
Project-URL: Homepage, https://github.com/natekspencer/pypentair
Project-URL: Repository, https://github.com/natekspencer/pypentair
